djclick/__init__.py
djclick/adapter.py
djclick/params.py
django_click-2.4.1.dist-info/LICENSE
django_click-2.4.1.dist-info/METADATA
django_click-2.4.1.dist-info/WHEEL
django_click-2.4.1.dist-info/top_level.txt
django_click-2.4.1.dist-info/RECORD
