Metadata-Version: 2.2
Name: django-click
Version: 2.4.1
Summary: Build Django management commands using the click CLI package.
Home-page: https://github.com/GaretJax/django-click
Author: Jonathan Stoppani
Author-email: jonathan@stoppani.name
License: MIT
Classifier: Development Status :: 4 - Beta
Classifier: Intended Audience :: Developers
Classifier: License :: OSI Approved :: MIT License
Classifier: Operating System :: OS Independent
Classifier: Programming Language :: Python
Classifier: Programming Language :: Python :: 3
Classifier: Programming Language :: Python :: 3.8
Classifier: Programming Language :: Python :: 3.9
Classifier: Programming Language :: Python :: 3.10
Classifier: Programming Language :: Python :: 3.11
Classifier: Programming Language :: Python :: 3.12
License-File: LICENSE
Requires-Dist: click>=7.1
Provides-Extra: a-sdist-g1-tp4b3-django-click-2-4-1-requirements-dev
Requires-Dist: Fabric; extra == "a-sdist-g1-tp4b3-django-click-2-4-1-requirements-dev"
Requires-Dist: livereload; extra == "a-sdist-g1-tp4b3-django-click-2-4-1-requirements-dev"
Requires-Dist: wheel; extra == "a-sdist-g1-tp4b3-django-click-2-4-1-requirements-dev"
Requires-Dist: check-manifest; extra == "a-sdist-g1-tp4b3-django-click-2-4-1-requirements-dev"
Requires-Dist: flake8; extra == "a-sdist-g1-tp4b3-django-click-2-4-1-requirements-dev"
Requires-Dist: mccabe; extra == "a-sdist-g1-tp4b3-django-click-2-4-1-requirements-dev"
Requires-Dist: pep8; extra == "a-sdist-g1-tp4b3-django-click-2-4-1-requirements-dev"
Requires-Dist: pep8-naming; extra == "a-sdist-g1-tp4b3-django-click-2-4-1-requirements-dev"
Requires-Dist: pyflakes; extra == "a-sdist-g1-tp4b3-django-click-2-4-1-requirements-dev"
Requires-Dist: Sphinx; extra == "a-sdist-g1-tp4b3-django-click-2-4-1-requirements-dev"
Requires-Dist: sphinx-autobuild; extra == "a-sdist-g1-tp4b3-django-click-2-4-1-requirements-dev"
Requires-Dist: sphinx_rtd_theme; extra == "a-sdist-g1-tp4b3-django-click-2-4-1-requirements-dev"
Provides-Extra: a-sdist-g1-tp4b3-django-click-2-4-1-requirements-test
Requires-Dist: pytest; extra == "a-sdist-g1-tp4b3-django-click-2-4-1-requirements-test"
Requires-Dist: coverage<5; extra == "a-sdist-g1-tp4b3-django-click-2-4-1-requirements-test"
Requires-Dist: pytest-django; extra == "a-sdist-g1-tp4b3-django-click-2-4-1-requirements-test"
Requires-Dist: pytest-cov; extra == "a-sdist-g1-tp4b3-django-click-2-4-1-requirements-test"
Requires-Dist: pytest-flake8; extra == "a-sdist-g1-tp4b3-django-click-2-4-1-requirements-test"
Dynamic: author
Dynamic: author-email
Dynamic: classifier
Dynamic: description
Dynamic: home-page
Dynamic: license
Dynamic: provides-extra
Dynamic: requires-dist
Dynamic: summary
